helixvis/__init__.py
helixvis/draw_wenxiang.py
helixvis/draw_wheel.py
helixvis-1.0.1.dist-info/LICENSE
helixvis-1.0.1.dist-info/METADATA
helixvis-1.0.1.dist-info/WHEEL
helixvis-1.0.1.dist-info/top_level.txt
helixvis-1.0.1.dist-info/RECORD
