Metadata-Version: 2.1
Name: helixvis
Version: 1.0.1
Summary: Create 2-dimensional visualizations of alpha-helical peptide sequences
Home-page: https://pypi.org/project/helixvis/
Author: Vigneshwar Subramanian, Raoul Wadhwa, Regina Stevens-Truss
Maintainer-email: vxs294@case.edu
License: GPL-3
Project-URL: Bug Tracker, https://github.com/subramv1/helixvis/issues
Project-URL: Documentation, https://github.com/subramv1/helixvis/blob/master/DOCUMENTATION.md
Project-URL: Source Code, https://github.com/subramv1/helixvis
Platform: UNKNOWN
Classifier: Development Status :: 5 - Production/Stable
Classifier: License :: OSI Approved :: GNU General Public License v3 (GPLv3)
Classifier: Programming Language :: Python
Classifier: Topic :: Scientific/Engineering :: Chemistry
Requires-Dist: numpy
Requires-Dist: pandas
Requires-Dist: matplotlib
